Workbook

Sheet 日次集計
A1: 日次集計
A2: 日付：2026年9月30日 ｜ BRIDGE HATCH 管理画面「月次レポート＞売上」より出力
A3: ※本書は売上集計表の見本（サンプル）です。記載のデータはすべて架空のものです。
A5: 【集計結果】
A6: 売上件数（件） | B6: =COUNT(取引一覧!A6:A20) -> 15
A7: 売上高（税抜） | B7: =取引一覧!G21 -> 1898000
A8: 消費税等（10%） | B8: =取引一覧!H21 -> 189800
A9: 売上高（税込） | B9: =取引一覧!I21 -> 2087800
A10: うち 月額利用料（税込） | B10: =SUMIFS(取引一覧!I6:I20,取引一覧!E6:E20,"月額利用料") -> 1870000
A11: うち ハニー追加購入（税込） | B11: =SUMIFS(取引一覧!I6:I20,取引一覧!E6:E20,"ハニー追加購入") -> 217800
A14: 【支払方法別】
A15: 支払方法 | B15: 件数 | C15: 税込金額(円)
A16: 銀行振込 | B16: =COUNTIF(取引一覧!J6:J20,"銀行振込") -> 8 | C16: =SUMIFS(取引一覧!I6:I20,取引一覧!J6:J20,"銀行振込") -> 1606000
A17: クレジットカード | B17: =COUNTIF(取引一覧!J6:J20,"クレジットカード") -> 7 | C17: =SUMIFS(取引一覧!I6:I20,取引一覧!J6:J20,"クレジットカード") -> 481800
A18: 合計 | B18: =SUM(B16:B17) -> 15 | C18: =SUM(C16:C17) -> 2087800
A21: 【区分別】
A22: 区分 | B22: 件数 | C22: 税抜(円) | D22: 消費税(円) | E22: 税込(円)
A23: 月額利用料 | B23: =COUNTIF(取引一覧!E6:E20,"月額利用料") -> 11 | C23: =SUMIFS(取引一覧!G6:G20,取引一覧!E6:E20,"月額利用料") -> 1700000 | D23: =SUMIFS(取引一覧!H6:H20,取引一覧!E6:E20,"月額利用料") -> 170000 | E23: =SUMIFS(取引一覧!I6:I20,取引一覧!E6:E20,"月額利用料") -> 1870000
A24: ハニー追加購入 | B24: =COUNTIF(取引一覧!E6:E20,"ハニー追加購入") -> 4 | C24: =SUMIFS(取引一覧!G6:G20,取引一覧!E6:E20,"ハニー追加購入") -> 198000 | D24: =SUMIFS(取引一覧!H6:H20,取引一覧!E6:E20,"ハニー追加購入") -> 19800 | E24: =SUMIFS(取引一覧!I6:I20,取引一覧!E6:E20,"ハニー追加購入") -> 217800
A25: 合計 | B25: =SUM(B23:B24) -> 15 | C25: =SUM(C23:C24) -> 1898000 | D25: =SUM(D23:D24) -> 189800 | E25: =SUM(E23:E24) -> 2087800

Sheet 取引一覧
A1: 取引一覧（精算結果）
A2: 対象日：2026年9月30日 ｜ BRIDGE HATCH 管理画面「月次レポート＞売上」より出力
A3: ※本書は売上集計表の見本（サンプル）です。記載のデータはすべて架空のものです。
A5: NO | B5: 取引日時 | C5: クライアントID | D5: クライアント名 | E5: 区分 | F5: プラン | G5: 税抜金額(円) | H5: 消費税(10%)(円) | I5: 税込金額(円) | J5: 支払方法 | K5: ステータス
A6: 1 | B6: 2026/09/30 09:12 | C6: CL-0001 | D6: 株式会社サンプル商事 | E6: 月額利用料 | F6: プレミアム | G6: 200000 | H6: =ROUND(G6*0.1,0) -> 20000 | I6: =G6+H6 -> 220000 | J6: 銀行振込 | K6: 入金済
A7: 2 | B7: 2026/09/30 09:40 | C7: CL-0002 | D7: 見本フーズ株式会社 | E7: 月額利用料 | F7: スタンダード | G7: 180000 | H7: =ROUND(G7*0.1,0) -> 18000 | I7: =G7+H7 -> 198000 | J7: 銀行振込 | K7: 入金済
A8: 3 | B8: 2026/09/30 10:05 | C8: CL-0003 | D8: サンプル工業株式会社 | E8: 月額利用料 | F8: ライト | G8: 60000 | H8: =ROUND(G8*0.1,0) -> 6000 | I8: =G8+H8 -> 66000 | J8: クレジットカード | K8: 決済済
A9: 4 | B9: 2026/09/30 10:31 | C9: CL-0004 | D9: 株式会社モデルハウス | E9: 月額利用料 | F9: プレミアム | G9: 200000 | H9: =ROUND(G9*0.1,0) -> 20000 | I9: =G9+H9 -> 220000 | J9: 銀行振込 | K9: 入金済
A10: 5 | B10: 2026/09/30 11:02 | C10: CL-0002 | D10: 見本フーズ株式会社 | E10: ハニー追加購入 | F10: - | G10: 60000 | H10: =ROUND(G10*0.1,0) -> 6000 | I10: =G10+H10 -> 66000 | J10: クレジットカード | K10: 決済済
A11: 6 | B11: 2026/09/30 11:47 | C11: CL-0005 | D11: ダミー物産株式会社 | E11: 月額利用料 | F11: スタンダード | G11: 180000 | H11: =ROUND(G11*0.1,0) -> 18000 | I11: =G11+H11 -> 198000 | J11: 銀行振込 | K11: 入金待ち
A12: 7 | B12: 2026/09/30 13:15 | C12: CL-0006 | D12: 株式会社テスト企画 | E12: 月額利用料 | F12: ライト | G12: 60000 | H12: =ROUND(G12*0.1,0) -> 6000 | I12: =G12+H12 -> 66000 | J12: クレジットカード | K12: 決済済
A13: 8 | B13: 2026/09/30 13:58 | C13: CL-0001 | D13: 株式会社サンプル商事 | E13: ハニー追加購入 | F13: - | G13: 12000 | H13: =ROUND(G13*0.1,0) -> 1200 | I13: =G13+H13 -> 13200 | J13: クレジットカード | K13: 決済済
A14: 9 | B14: 2026/09/30 14:22 | C14: CL-0007 | D14: 見本堂株式会社 | E14: 月額利用料 | F14: プレミアム | G14: 200000 | H14: =ROUND(G14*0.1,0) -> 20000 | I14: =G14+H14 -> 220000 | J14: 銀行振込 | K14: 入金済
A15: 10 | B15: 2026/09/30 15:10 | C15: CL-0008 | D15: サンプル観光株式会社 | E15: 月額利用料 | F15: スタンダード | G15: 180000 | H15: =ROUND(G15*0.1,0) -> 18000 | I15: =G15+H15 -> 198000 | J15: 銀行振込 | K15: 入金済
A16: 11 | B16: 2026/09/30 15:44 | C16: CL-0009 | D16: 株式会社ダミー製作所 | E16: 月額利用料 | F16: ライト | G16: 60000 | H16: =ROUND(G16*0.1,0) -> 6000 | I16: =G16+H16 -> 66000 | J16: クレジットカード | K16: 決済済
A17: 12 | B17: 2026/09/30 16:20 | C17: CL-0003 | D17: サンプル工業株式会社 | E17: ハニー追加購入 | F17: - | G17: 120000 | H17: =ROUND(G17*0.1,0) -> 12000 | I17: =G17+H17 -> 132000 | J17: 銀行振込 | K17: 入金済
... A20: 15 | B20: 2026/09/30 18:02 | C20: CL-0011 | D20: 株式会社サンプル印刷 | E20: 月額利用料 | F20: スタンダード | G20: 180000 | H20: =ROUND(G20*0.1,0) -> 18000 | I20: =G20+H20 -> 198000 | J20: クレジットカード | K20: 決済済
F21: 合計 | G21: =SUM(G6:G20) -> 1898000 | H21: =SUM(H6:H20) -> 189800 | I21: =SUM(I6:I20) -> 2087800
A23: ※軽減税率（8%）対象の取引はありません。すべて標準税率（10%）です。

Sheet 明細一覧
A1: 明細一覧
A2: 対象日：2026年9月30日 ｜ 請求書番号つき明細（BRIDGE HATCH 請求書発行機能と連動）
A3: ※本書は売上集計表の見本（サンプル）です。記載のデータはすべて架空のものです。
A5: 請求書番号 | B5: クライアントID | C5: 取引年月日 | D5: 区分 | E5: 摘要 | F5: 税抜金額(円) | G5: 消費税(10%)(円) | H5: 税込金額(円) | I5: 支払方法 | J5: 入金状況 | K5: 領収書
A6: INV-202609-0001 | B6: CL-0001 | C6: 2026/09/30 | D6: 月額利用料 | E6: BRIDGE HATCH ツール利用料（プレミアム・2026年9月分） | F6: =取引一覧!G6 -> 200000 | G6: =取引一覧!H6 -> 20000 | H6: =取引一覧!I6 -> 220000 | I6: 銀行振込 | J6: 済 | K6: 発行済
A7: INV-202609-0002 | B7: CL-0002 | C7: 2026/09/30 | D7: 月額利用料 | E7: BRIDGE HATCH ツール利用料（スタンダード・2026年9月分） | F7: =取引一覧!G7 -> 180000 | G7: =取引一覧!H7 -> 18000 | H7: =取引一覧!I7 -> 198000 | I7: 銀行振込 | J7: 済 | K7: 発行済
A8: INV-202609-0003 | B8: CL-0003 | C8: 2026/09/30 | D8: 月額利用料 | E8: BRIDGE HATCH ツール利用料（ライト・2026年9月分） | F8: =取引一覧!G8 -> 60000 | G8: =取引一覧!H8 -> 6000 | H8: =取引一覧!I8 -> 66000 | I8: クレジットカード | J8: 済 | K8: 発行済
A9: INV-202609-0004 | B9: CL-0004 | C9: 2026/09/30 | D9: 月額利用料 | E9: BRIDGE HATCH ツール利用料（プレミアム・2026年9月分） | F9: =取引一覧!G9 -> 200000 | G9: =取引一覧!H9 -> 20000 | H9: =取引一覧!I9 -> 220000 | I9: 銀行振込 | J9: 済 | K9: 発行済
A10: INV-202609-0005 | B10: CL-0002 | C10: 2026/09/30 | D10: ハニー追加購入 | E10: ハニー（ポイント）追加購入 | F10: =取引一覧!G10 -> 60000 | G10: =取引一覧!H10 -> 6000 | H10: =取引一覧!I10 -> 66000 | I10: クレジットカード | J10: 済 | K10: 発行済
A11: INV-202609-0006 | B11: CL-0005 | C11: 2026/09/30 | D11: 月額利用料 | E11: BRIDGE HATCH ツール利用料（スタンダード・2026年9月分） | F11: =取引一覧!G11 -> 180000 | G11: =取引一覧!H11 -> 18000 | H11: =取引一覧!I11 -> 198000 | I11: 銀行振込 | J11: 未 | K11: 発行済
A12: INV-202609-0007 | B12: CL-0006 | C12: 2026/09/30 | D12: 月額利用料 | E12: BRIDGE HATCH ツール利用料（ライト・2026年9月分） | F12: =取引一覧!G12 -> 60000 | G12: =取引一覧!H12 -> 6000 | H12: =取引一覧!I12 -> 66000 | I12: クレジットカード | J12: 済 | K12: 発行済
A13: INV-202609-0008 | B13: CL-0001 | C13: 2026/09/30 | D13: ハニー追加購入 | E13: ハニー（ポイント）追加購入 | F13: =取引一覧!G13 -> 12000 | G13: =取引一覧!H13 -> 1200 | H13: =取引一覧!I13 -> 13200 | I13: クレジットカード | J13: 済 | K13: 発行済
A14: INV-202609-0009 | B14: CL-0007 | C14: 2026/09/30 | D14: 月額利用料 | E14: BRIDGE HATCH ツール利用料（プレミアム・2026年9月分） | F14: =取引一覧!G14 -> 200000 | G14: =取引一覧!H14 -> 20000 | H14: =取引一覧!I14 -> 220000 | I14: 銀行振込 | J14: 済 | K14: 発行済
A15: INV-202609-0010 | B15: CL-0008 | C15: 2026/09/30 | D15: 月額利用料 | E15: BRIDGE HATCH ツール利用料（スタンダード・2026年9月分） | F15: =取引一覧!G15 -> 180000 | G15: =取引一覧!H15 -> 18000 | H15: =取引一覧!I15 -> 198000 | I15: 銀行振込 | J15: 済 | K15: 発行済
A16: INV-202609-0011 | B16: CL-0009 | C16: 2026/09/30 | D16: 月額利用料 | E16: BRIDGE HATCH ツール利用料（ライト・2026年9月分） | F16: =取引一覧!G16 -> 60000 | G16: =取引一覧!H16 -> 6000 | H16: =取引一覧!I16 -> 66000 | I16: クレジットカード | J16: 済 | K16: 発行済
A17: INV-202609-0012 | B17: CL-0003 | C17: 2026/09/30 | D17: ハニー追加購入 | E17: ハニー（ポイント）追加購入 | F17: =取引一覧!G17 -> 120000 | G17: =取引一覧!H17 -> 12000 | H17: =取引一覧!I17 -> 132000 | I17: 銀行振込 | J17: 済 | K17: 発行済
... A20: INV-202609-0015 | B20: CL-0011 | C20: 2026/09/30 | D20: 月額利用料 | E20: BRIDGE HATCH ツール利用料（スタンダード・2026年9月分） | F20: =取引一覧!G20 -> 180000 | G20: =取引一覧!H20 -> 18000 | H20: =取引一覧!I20 -> 198000 | I20: クレジットカード | J20: 済 | K20: 発行済
E21: 合計 | F21: =SUM(F6:F20) -> 1898000 | G21: =SUM(G6:G20) -> 189800 | H21: =SUM(H6:H20) -> 2087800
A23: ※軽減税率（8%）対象の取引はありません。金額・名称はすべて架空のサンプルです。
